__init__.py
m2h/__init__.py
m2h/__version__.py
m2h/lang.py
m2h/m2h.py
m2h/py.typed
machine2human-0.1.2.dist-info/licenses/LICENSE
machine2human-0.1.2.dist-info/METADATA
machine2human-0.1.2.dist-info/WHEEL
machine2human-0.1.2.dist-info/top_level.txt
machine2human-0.1.2.dist-info/RECORD
