Metadata-Version: 2.4
Name: machine2human
Version: 0.1.2
Summary: Make machine more friendly to you! Convert seconds to a human string and back!
Author-email: andrew000 <help@kusbot.com>
License-Expression: MIT
Keywords: m2h
Classifier: Programming Language :: Python :: Implementation :: CPython
Classifier: Programming Language :: Python :: 3
Classifier: Programming Language :: Python :: 3.10
Classifier: Programming Language :: Python :: 3.11
Classifier: Programming Language :: Python :: 3.12
Classifier: Programming Language :: Python :: 3.13
Classifier: Programming Language :: Python :: 3.14
Requires-Python: >=3.10
License-File: LICENSE
Provides-Extra: dev
Requires-Dist: isort==6.0.1; extra == "dev"
Requires-Dist: mypy==1.18.2; extra == "dev"
Requires-Dist: pre-commit==4.3.0; extra == "dev"
Requires-Dist: ruff==0.13.1; extra == "dev"
Requires-Dist: setuptools==80.9.0; extra == "dev"
Requires-Dist: wheel==0.45.1; extra == "dev"
Provides-Extra: tests
Requires-Dist: coverage==7.10.6; extra == "tests"
Requires-Dist: pytest-cov==7.0.0; extra == "tests"
Requires-Dist: pytest-html==4.1.1; extra == "tests"
Requires-Dist: pytest==8.4.2; extra == "tests"
Dynamic: license-file
